ibeamer/__init__.py
ibeamer/_version.py
ibeamer-6.9.0.data/data/share/jupyter/labextensions/ibeamer/build_log.json
ibeamer-6.9.0.data/data/share/jupyter/labextensions/ibeamer/package.json
ibeamer-6.9.0.data/data/share/jupyter/labextensions/ibeamer/static/lib_index_js.4fbdccf9b33fd694973e.js
ibeamer-6.9.0.data/data/share/jupyter/labextensions/ibeamer/static/lib_index_js.4fbdccf9b33fd694973e.js.map
ibeamer-6.9.0.data/data/share/jupyter/labextensions/ibeamer/static/remoteEntry.7fc808580f20e90ac6d0.js
ibeamer-6.9.0.data/data/share/jupyter/labextensions/ibeamer/static/remoteEntry.7fc808580f20e90ac6d0.js.map
ibeamer-6.9.0.data/data/share/jupyter/labextensions/ibeamer/static/style.js
ibeamer-6.9.0.data/data/share/jupyter/labextensions/ibeamer/static/style_index_js.4cdef37111d3a5ad1434.js
ibeamer-6.9.0.data/data/share/jupyter/labextensions/ibeamer/static/style_index_js.4cdef37111d3a5ad1434.js.map
ibeamer-6.9.0.data/data/share/jupyter/labextensions/ibeamer/install.json
ibeamer-6.9.0.dist-info/METADATA
ibeamer-6.9.0.dist-info/WHEEL
ibeamer-6.9.0.dist-info/licenses/LICENSE
ibeamer-6.9.0.dist-info/RECORD
